agent_brain_cli/__init__.py
agent_brain_cli/cli.py
agent_brain_cli/client/__init__.py
agent_brain_cli/client/api_client.py
agent_brain_cli/commands/__init__.py
agent_brain_cli/commands/index.py
agent_brain_cli/commands/init.py
agent_brain_cli/commands/list_cmd.py
agent_brain_cli/commands/query.py
agent_brain_cli/commands/reset.py
agent_brain_cli/commands/start.py
agent_brain_cli/commands/status.py
agent_brain_cli/commands/stop.py
agent_brain_cli-1.2.0.dist-info/METADATA
agent_brain_cli-1.2.0.dist-info/WHEEL
agent_brain_cli-1.2.0.dist-info/entry_points.txt
agent_brain_cli-1.2.0.dist-info/RECORD
