Metadata-Version: 2.3
Name: agent-brain-cli
Version: 1.2.0
Summary: Agent Brain CLI - Command-line interface for managing AI agent memory and knowledge retrieval
License: MIT
Keywords: agent-brain,rag,cli,ai-memory,llm-memory,semantic-search,ai-agent,claude-code,agent-memory
Author: Spillwave Solutions
Requires-Python: >=3.10,<4.0
Classifier: Development Status :: 4 - Beta
Classifier: Environment :: Console
Classifier: Intended Audience :: Developers
Classifier: License :: OSI Approved :: MIT License
Classifier: Programming Language :: Python :: 3
Classifier: Programming Language :: Python :: 3.10
Classifier: Programming Language :: Python :: 3.11
Classifier: Programming Language :: Python :: 3.12
Classifier: Programming Language :: Python :: 3.13
Requires-Dist: click (>=8.1.0,<9.0.0)
Requires-Dist: httpx (>=0.28.0,<0.29.0)
Requires-Dist: rich (>=13.9.0,<14.0.0)
Project-URL: Homepage, https://github.com/SpillwaveSolutions/doc-serve
Project-URL: Repository, https://github.com/SpillwaveSolutions/doc-serve
